NEST/__init__.py
NEST/_version.py
NEST/cmaps.npz
NEST/core.py
NEST/domain.pkl
NEST/tutorial.ipynb
NEST/models/BaSTI.mlp
NEST/models/BaSTI_BPRP.mlp
NEST/models/BaSTI_HST.mlp
NEST/models/BaSTI_HST.scaler
NEST/models/BaSTI_HST_BPRP.mlp
NEST/models/BaSTI_HST_enhanced.mlp
NEST/models/BaSTI_HST_enhanced_BPRP.mlp
NEST/models/Dartmouth.mlp
NEST/models/Dartmouth_BPRP.mlp
NEST/models/Geneva.mlp
NEST/models/Geneva_BPRP.mlp
NEST/models/MIST.mlp
NEST/models/MIST_BPRP.mlp
NEST/models/PARSEC.mlp
NEST/models/PARSEC_BPRP.mlp
NEST/models/YaPSI.mlp
NEST/models/YaPSI_BPRP.mlp
astro_nest-0.9.1.dist-info/METADATA
astro_nest-0.9.1.dist-info/WHEEL
astro_nest-0.9.1.dist-info/top_level.txt
astro_nest-0.9.1.dist-info/RECORD
