Metadata-Version: 2.4
Name: astro-nest
Version: 0.9.1
Summary: A python package that provides neural networks to estimate ages of stars.
Author-email: Tristan Boin <tristan.boin@obspm.fr>
License-Expression: MIT
Project-URL: Homepage, https://star-age.github.io/NEST-docs/
Classifier: Intended Audience :: Science/Research
Classifier: Operating System :: OS Independent
Classifier: Programming Language :: Python :: 3
Classifier: Topic :: Scientific/Engineering :: Astronomy
